{"stats":{"minecraft:picked_up":{"minecraft:lingering_potion":3,"minecraft:golden_carrot":1,"minecraft:splash_potion":22,"minecraft:iron_trapdoor":97,"minecraft:ladder":4,"minecraft:water_bucket":2,"minecraft:cobblestone_stairs":1,"minecraft:dirt":160,"minecraft:string":3,"tacz:ammo_box":1,"tacz:ammo":84,"minecraft:bone":1,"minecraft:experience_bottle":1,"create:redstone_link":4,"minecraft:oak_sign":14,"minecraft:reinforced_deepslate":192,"minecraft:wheat_seeds":2,"minecraft:tnt_minecart":2,"minecraft:bucket":1,"minecraft:redstone_torch":5,"tacz:gun_smith_table":1,"minecraft:chiseled_polished_blackstone":8,"minecraft:oak_door":2,"minecraft:torch":4,"minecraft:lava_bucket":1,"vs_eureka:light_blue_balloon":1,"minecraft:magenta_shulker_box":2,"minecraft:white_bed":3,"minecraft:grass_block":1,"minecraft:netherite_pickaxe":1,"minecraft:mossy_cobblestone":1,"create:industrial_iron_block":83,"minecraft:firework_rocket":64,"minecraft:netherite_helmet":1,"create:experience_nugget":130,"tacz:modern_kinetic_gun":6,"minecraft:iron_block":392,"vs_eureka:ballast":1,"minecraft:totem_of_undying":3,"minecraft:obsidian":3,"minecraft:smooth_quartz_slab":2,"minecraft:iron_bars":28,"minecraft:snowball":12,"minecraft:cobblestone":37,"minecraft:ender_pearl":32},"minecraft:killed":{"minecraft:player":36},"minecraft:custom":{"minecraft:open_shulker_box":10,"minecraft:leave_game":13,"minecraft:time_since_death":50946,"minecraft:sleep_in_bed":1,"minecraft:climb_one_cm":33249,"minecraft:damage_resisted":6013,"minecraft:time_since_rest":50971,"minecraft:sprint_one_cm":217080,"minecraft:damage_absorbed":3400,"minecraft:damage_taken":1172720,"minecraft:walk_one_cm":465742,"minecraft:damage_blocked_by_shield":3530,"minecraft:drop":104,"minecraft:damage_dealt":2896,"minecraft:swim_one_cm":4674,"minecraft:fly_one_cm":1929292,"minecraft:player_kills":93,"minecraft:open_chest":1,"minecraft:play_time":298206,"minecraft:crouch_one_cm":52481,"minecraft:deaths":79,"minecraft:sneak_time":30171,"minecraft:walk_under_water_one_cm":12252,"minecraft:aviate_one_cm":333260,"minecraft:jump":2204,"minecraft:walk_on_water_one_cm":18068,"minecraft:total_world_time":298206,"minecraft:fall_one_cm":18000863},"minecraft:mined":{"minecraft:white_bed":2,"minecraft:mossy_cobblestone":1,"minecraft:cobblestone":1,"minecraft:wall_torch":2,"minecraft:carrots":1,"minecraft:wheat":2,"minecraft:fire":18,"create:industrial_iron_block":18,"minecraft:potatoes":1,"minecraft:iron_block":3},"minecraft:dropped":{"minecraft:oak_door":1,"minecraft:water_bucket":2,"vs_eureka:light_blue_balloon":2,"minecraft:wheat_seeds":1,"minecraft:glass_bottle":2,"minecraft:mossy_cobblestone":1,"minecraft:ender_pearl":32,"minecraft:obsidian":3,"minecraft:netherite_helmet":3,"minecraft:netherite_chestplate":3,"minecraft:experience_bottle":1,"minecraft:cobblestone":37,"create:experience_nugget":130,"minecraft:oak_sign":15,"minecraft:elytra":1,"minecraft:netherite_leggings":3,"minecraft:cobblestone_stairs":1,"minecraft:lava_bucket":1,"minecraft:iron_block":200,"minecraft:dirt":130,"minecraft:iron_trapdoor":27,"minecraft:golden_carrot":1,"minecraft:white_concrete":1,"minecraft:tnt_minecart":1,"minecraft:wooden_axe":4,"minecraft:lingering_potion":3,"minecraft:netherite_boots":3,"createbigcannons:unbored_medium_nethersteel_cannon_layer":1,"minecraft:ladder":4,"minecraft:carved_pumpkin":1,"tacz:modern_kinetic_gun":2,"tacz:ammo":97,"create:industrial_iron_block":88,"minecraft:bucket":1,"minecraft:splash_potion":22,"minecraft:firework_rocket":167},"minecraft:killed_by":{"minecraft:player":56},"minecraft:used":{"minecraft:chiseled_polished_blackstone":39,"minecraft:netherite_sword":38,"minecraft:water_bucket":7,"minecraft:lodestone":15,"minecraft:carved_pumpkin":1,"minecraft:netherite_chestplate":1,"minecraft:ender_pearl":48,"minecraft:oak_sign":53,"tacz:gun_smith_table":3,"minecraft:shield":26,"minecraft:redstone_block":47,"minecraft:oak_door":1,"minecraft:torch":1,"vs_eureka:ballast":4,"minecraft:respawn_anchor":14,"minecraft:netherite_leggings":1,"minecraft:tnt":333,"minecraft:red_bed":2,"vs_clockwork:wanderlite_deepslate_ore":4,"minecraft:netherite_helmet":1,"minecraft:white_bed":1,"minecraft:lingering_potion":3,"minecraft:end_stone":982,"vs_clockwork:physics_infuser":3,"minecraft:redstone_torch":61,"minecraft:wooden_axe":1,"minecraft:lava_bucket":192,"minecraft:firework_rocket":26,"minecraft:iron_block":329,"minecraft:light_blue_bed":1,"createbigcannons:nethersteel_block":6,"minecraft:totem_of_undying":8,"minecraft:netherite_boots":1,"minecraft:blackstone_slab":410,"minecraft:bedrock":2,"minecraft:reinforced_deepslate":366,"minecraft:golden_carrot":38,"minecraft:potion":2,"minecraft:iron_trapdoor":6,"create:industrial_iron_block":295,"minecraft:bucket":6,"minecraft:netherite_pickaxe":23,"minecraft:white_concrete":5,"minecraft:magenta_shulker_box":2,"minecraft:splash_potion":10,"minecraft:experience_bottle":67,"cbcmodernwarfare:composite_block":2,"minecraft:enchanted_golden_apple":31}},"DataVersion":3465}